<?xml version="1.0" encoding="UTF-8"?>
<data>
	<classes>
		<vowel>aeiou</vowel>
		<consonant>bcdfghjklmnpqrstvwxyz</consonant>
		<casesensitive>oiudgjnrstyz</casesensitive>
	</classes>
	<patterns>
		<pattern>
			<find>psh</find>
			<replace>পশ</replace>
			<rules/>
		</pattern>
		<pattern>
			<find>bhl</find>
			<replace>ভ্ল</replace>
			<rules/>
		</pattern>
		<pattern>
			<find>bdh</find>
			<replace>ব্ধ</replace>
			<rules/>
		</pattern>
		<pattern>
			<find>bj</find>
			<replace>ব্জ</replace>
			<rules/>
		</pattern>
		<pattern>
			<find>bd</find>
			<replace>ব্দ</replace>
			<rules/>
		</pattern>
		<pattern>
			<find>bb</find>
			<replace>ব্ব</replace>
			<rules/>
		</pattern>
		<pattern>
			<find>bl</find>
			<replace>ব্ল</replace>
			<rules/>
		</pattern>
		<pattern>
			<find>bh</find>
			<replace>ভ</replace>
			<rules/>
		</pattern>
		<pattern>
			<find>vl</find>
			<replace>ভ্ল</replace>
			<rules/>
		</pattern>
		<pattern>
			<find>b</find>
			<replace>ব</replace>
			<rules/>
		</pattern>
		<pattern>
			<find>v</find>
			<replace>ভ</replace>
			<rules/>
		</pattern>
		<pattern>
			<find>cNG</find>
			<replace>চ্ঞ</replace>
			<rules/>
		</pattern>
		<pattern>
			<find>cch</find>
			<replace>চ্ছ</replace>
			<rules/>
		</pattern>
		<pattern>
			<find>cc</find>
			<replace>চ্চ</replace>
			<rules/>
		</pattern>
		<pattern>
			<find>ch</find>
			<replace>ছ</replace>
			<rules/>
		</pattern>
		<pattern>
			<find>c</find>
			<replace>চ</replace>
			<rules/>
		</pattern>
		<pattern>
			<find>dhn</find>
			<replace>ধ্ন</replace>
			<rules/>
		</pattern>
		<pattern>
			<find>dhm</find>
			<replace>ধ্ম</replace>
			<rules/>
		</pattern>
		<pattern>
			<find>dgh</find>
			<replace>দ্ঘ</replace>
			<rules/>
		</pattern>
		<pattern>
			<find>ddh</find>
			<replace>দ্ধ</replace>
			<rules/>
		</pattern>
		<pattern>
			<find>dbh</find>
			<replace>দ্ভ</replace>
			<rules/>
		</pattern>
		<pattern>
			<find>dv</find>
			<replace>দ্ভ</replace>
			<rules/>
		</pattern>
		<pattern>
			<find>dm</find>
			<replace>দ্ম</replace>
			<rules/>
		</pattern>
		<pattern>
			<find>DD</find>
			<replace>ড্ড</replace>
			<rules/>
		</pattern>
		<pattern>
			<find>Dh</find>
			<replace>ঢ</replace>
			<rules/>
		</pattern>
		<pattern>
			<find>dh</find>
			<replace>ধ</replace>
			<rules/>
		</pattern>
		<pattern>
			<find>dg</find>
			<replace>দ্গ</replace>
			<rules/>
		</pattern>
		<pattern>
			<find>dd</find>
			<replace>দ্দ</replace>
			<rules/>
		</pattern>
		<pattern>
			<find>D</find>
			<replace>ড</replace>
			<rules/>
		</pattern>
		<pattern>
			<find>d</find>
			<replace>দ</replace>
			<rules/>
		</pattern>
		<pattern>
			<find>...</find>
			<replace>...</replace>
			<rules/>
		</pattern>
		<pattern>
			<find>.`</find>
			<replace>.</replace>
			<rules/>
		</pattern>
		<pattern>
			<find>..</find>
			<replace>।।</replace>
			<rules/>
		</pattern>
		<pattern>
			<find>.</find>
			<replace>।</replace>
			<rules/>
		</pattern>
		<pattern>
			<find>ghn</find>
			<replace>ঘ্ন</replace>
			<rules/>
		</pattern>
		<pattern>
			<find>Ghn</find>
			<replace>ঘ্ন</replace>
			<rules/>
		</pattern>
		<pattern>
			<find>gdh</find>
			<replace>গ্ধ</replace>
			<rules/>
		</pattern>
		<pattern>
			<find>Gdh</find>
			<replace>গ্ধ</replace>
			<rules/>
		</pattern>
		<pattern>
			<find>gN</find>
			<replace>গ্ণ</replace>
			<rules/>
		</pattern>
		<pattern>
			<find>GN</find>
			<replace>গ্ণ</replace>
			<rules/>
		</pattern>
		<pattern>
			<find>gn</find>
			<replace>গ্ন</replace>
			<rules/>
		</pattern>
		<pattern>
			<find>Gn</find>
			<replace>গ্ন</replace>
			<rules/>
		</pattern>
		<pattern>
			<find>gm</find>
			<replace>গ্ম</replace>
			<rules/>
		</pattern>
		<pattern>
			<find>Gm</find>
			<replace>গ্ম</replace>
			<rules/>
		</pattern>
		<pattern>
			<find>gl</find>
			<replace>গ্ল</replace>
			<rules/>
		</pattern>
		<pattern>
			<find>Gl</find>
			<replace>গ্ল</replace>
			<rules/>
		</pattern>
		<pattern>
			<find>gg</find>
			<replace>জ্ঞ</replace>
			<rules/>
		</pattern>
		<pattern>
			<find>GG</find>
			<replace>জ্ঞ</replace>
			<rules/>
		</pattern>
		<pattern>
			<find>Gg</find>
			<replace>জ্ঞ</replace>
			<rules/>
		</pattern>
		<pattern>
			<find>gG</find>
			<replace>জ্ঞ</replace>
			<rules/>
		</pattern>
		<pattern>
			<find>gh</find>
			<replace>ঘ</replace>
			<rules/>
		</pattern>
		<pattern>
			<find>Gh</find>
			<replace>ঘ</replace>
			<rules/>
		</pattern>
		<pattern>
			<find>g</find>
			<replace>গ</replace>
			<rules/>
		</pattern>
		<pattern>
			<find>G</find>
			<replace>গ</replace>
			<rules/>
		</pattern>
		<pattern>
			<find>hN</find>
			<replace>হ্ণ</replace>
			<rules/>
		</pattern>
		<pattern>
			<find>hn</find>
			<replace>হ্ন</replace>
			<rules/>
		</pattern>
		<pattern>
			<find>hm</find>
			<replace>হ্ম</replace>
			<rules/>
		</pattern>
		<pattern>
			<find>hl</find>
			<replace>হ্ল</replace>
			<rules/>
		</pattern>
		<pattern>
			<find>h</find>
			<replace>হ</replace>
			<rules/>
		</pattern>
		<pattern>
			<find>jjh</find>
			<replace>জ্ঝ</replace>
			<rules/>
		</pattern>
		<pattern>
			<find>jNG</find>
			<replace>জ্ঞ</replace>
			<rules/>
		</pattern>
		<pattern>
			<find>jh</find>
			<replace>ঝ</replace>
			<rules/>
		</pattern>
		<pattern>
			<find>jj</find>
			<replace>জ্জ</replace>
			<rules/>
		</pattern>
		<pattern>
			<find>j</find>
			<replace>জ</replace>
			<rules/>
		</pattern>
		<pattern>
			<find>J</find>
			<replace>জ</replace>
			<rules/>
		</pattern>
		<pattern>
			<find>kkhN</find>
			<replace>ক্ষ্ণ</replace>
			<rules/>
		</pattern>
		<pattern>
			<find>kShN</find>
			<replace>ক্ষ্ণ</replace>
			<rules/>
		</pattern>
		<pattern>
			<find>kkhm</find>
			<replace>ক্ষ্ম</replace>
			<rules/>
		</pattern>
		<pattern>
			<find>kShm</find>
			<replace>ক্ষ্ম</replace>
			<rules/>
		</pattern>
		<pattern>
			<find>kxN</find>
			<replace>ক্ষ্ণ</replace>
			<rules/>
		</pattern>
		<pattern>
			<find>kxm</find>
			<replace>ক্ষ্ম</replace>
			<rules/>
		</pattern>
		<pattern>
			<find>kkh</find>
			<replace>ক্ষ</replace>
			<rules/>
		</pattern>
		<pattern>
			<find>kSh</find>
			<replace>ক্ষ</replace>
			<rules/>
		</pattern>
		<pattern>
			<find>ksh</find>
			<replace>কশ</replace>
			<rules/>
		</pattern>
		<pattern>
			<find>kx</find>
			<replace>ক্ষ</replace>
			<rules/>
		</pattern>
		<pattern>
			<find>kk</find>
			<replace>ক্ক</replace>
			<rules/>
		</pattern>
		<pattern>
			<find>kT</find>
			<replace>ক্ট</replace>
			<rules/>
		</pattern>
		<pattern>
			<find>kt</find>
			<replace>ক্ত</replace>
			<rules/>
		</pattern>
		<pattern>
			<find>kl</find>
			<replace>ক্ল</replace>
			<rules/>
		</pattern>
		<pattern>
			<find>ks</find>
			<replace>ক্স</replace>
			<rules/>
		</pattern>
		<pattern>
			<find>kh</find>
			<replace>খ</replace>
			<rules/>
		</pattern>
		<pattern>
			<find>k</find>
			<replace>ক</replace>
			<rules/>
		</pattern>
		<pattern>
			<find>lbh</find>
			<replace>ল্ভ</replace>
			<rules/>
		</pattern>
		<pattern>
			<find>ldh</find>
			<replace>ল্ধ</replace>
			<rules/>
		</pattern>
		<pattern>
			<find>lkh</find>
			<replace>লখ</replace>
			<rules/>
		</pattern>
		<pattern>
			<find>lgh</find>
			<replace>লঘ</replace>
			<rules/>
		</pattern>
		<pattern>
			<find>lph</find>
			<replace>লফ</replace>
			<rules/>
		</pattern>
		<pattern>
			<find>lk</find>
			<replace>ল্ক</replace>
			<rules/>
		</pattern>
		<pattern>
			<find>lg</find>
			<replace>ল্গ</replace>
			<rules/>
		</pattern>
		<pattern>
			<find>lT</find>
			<replace>ল্ট</replace>
			<rules/>
		</pattern>
		<pattern>
			<find>lD</find>
			<replace>ল্ড</replace>
			<rules/>
		</pattern>
		<pattern>
			<find>lp</find>
			<replace>ল্প</replace>
			<rules/>
		</pattern>
		<pattern>
			<find>lv</find>
			<replace>ল্ভ</replace>
			<rules/>
		</pattern>
		<pattern>
			<find>lm</find>
			<replace>ল্ম</replace>
			<rules/>
		</pattern>
		<pattern>
			<find>ll</find>
			<replace>ল্ল</replace>
			<rules/>
		</pattern>
		<pattern>
			<find>lb</find>
			<replace>ল্ব</replace>
			<rules/>
		</pattern>
		<pattern>
			<find>l</find>
			<replace>ল</replace>
			<rules/>
		</pattern>
		<pattern>
			<find>mth</find>
			<replace>ম্থ</replace>
			<rules/>
		</pattern>
		<pattern>
			<find>mph</find>
			<replace>ম্ফ</replace>
			<rules/>
		</pattern>
		<pattern>
			<find>mbh</find>
			<replace>ম্ভ</replace>
			<rules/>
		</pattern>
		<pattern>
			<find>mpl</find>
			<replace>মপ্ল</replace>
			<rules/>
		</pattern>
		<pattern>
			<find>mn</find>
			<replace>ম্ন</replace>
			<rules/>
		</pattern>
		<pattern>
			<find>mp</find>
			<replace>ম্প</replace>
			<rules/>
		</pattern>
		<pattern>
			<find>mv</find>
			<replace>ম্ভ</replace>
			<rules/>
		</pattern>
		<pattern>
			<find>mm</find>
			<replace>ম্ম</replace>
			<rules/>
		</pattern>
		<pattern>
			<find>ml</find>
			<replace>ম্ল</replace>
			<rules/>
		</pattern>
		<pattern>
			<find>mb</find>
			<replace>ম্ব</replace>
			<rules/>
		</pattern>
		<pattern>
			<find>mf</find>
			<replace>ম্ফ</replace>
			<rules/>
		</pattern>
		<pattern>
			<find>m</find>
			<replace>ম</replace>
			<rules/>
		</pattern>
		<pattern>
			<find>0</find>
			<replace>০</replace>
			<rules/>
		</pattern>
		<pattern>
			<find>1</find>
			<replace>১</replace>
			<rules/>
		</pattern>
		<pattern>
			<find>2</find>
			<replace>২</replace>
			<rules/>
		</pattern>
		<pattern>
			<find>3</find>
			<replace>৩</replace>
			<rules/>
		</pattern>
		<pattern>
			<find>4</find>
			<replace>৪</replace>
			<rules/>
		</pattern>
		<pattern>
			<find>5</find>
			<replace>৫</replace>
			<rules/>
		</pattern>
		<pattern>
			<find>6</find>
			<replace>৬</replace>
			<rules/>
		</pattern>
		<pattern>
			<find>7</find>
			<replace>৭</replace>
			<rules/>
		</pattern>
		<pattern>
			<find>8</find>
			<replace>৮</replace>
			<rules/>
		</pattern>
		<pattern>
			<find>9</find>
			<replace>৯</replace>
			<rules/>
		</pattern>
		<pattern>
			<find>NgkSh</find>
			<replace>ঙ্ক্ষ</replace>
			<rules/>
		</pattern>
		<pattern>
			<find>Ngkkh</find>
			<replace>ঙ্ক্ষ</replace>
			<rules/>
		</pattern>
		<pattern>
			<find>NGch</find>
			<replace>ঞ্ছ</replace>
			<rules/>
		</pattern>
		<pattern>
			<find>Nggh</find>
			<replace>ঙ্ঘ</replace>
			<rules/>
		</pattern>
		<pattern>
			<find>Ngkh</find>
			<replace>ঙ্খ</replace>
			<rules/>
		</pattern>
		<pattern>
			<find>NGjh</find>
			<replace>ঞ্ঝ</replace>
			<rules/>
		</pattern>
		<pattern>
			<find>ngOU</find>
			<replace>ঙ্গৌ</replace>
			<rules/>
		</pattern>
		<pattern>
			<find>ngOI</find>
			<replace>ঙ্গৈ</replace>
			<rules/>
		</pattern>
		<pattern>
			<find>Ngkx</find>
			<replace>ঙ্ক্ষ</replace>
			<rules/>
		</pattern>
		<pattern>
			<find>NGc</find>
			<replace>ঞ্চ</replace>
			<rules/>
		</pattern>
		<pattern>
			<find>nch</find>
			<replace>ঞ্ছ</replace>
			<rules/>
		</pattern>
		<pattern>
			<find>njh</find>
			<replace>ঞ্ঝ</replace>
			<rules/>
		</pattern>
		<pattern>
			<find>ngh</find>
			<replace>ঙ্ঘ</replace>
			<rules/>
		</pattern>
		<pattern>
			<find>Ngk</find>
			<replace>ঙ্ক</replace>
			<rules/>
		</pattern>
		<pattern>
			<find>Ngx</find>
			<replace>ঙ্ষ</replace>
			<rules/>
		</pattern>
		<pattern>
			<find>Ngg</find>
			<replace>ঙ্গ</replace>
			<rules/>
		</pattern>
		<pattern>
			<find>Ngm</find>
			<replace>ঙ্ম</replace>
			<rules/>
		</pattern>
		<pattern>
			<find>NGj</find>
			<replace>ঞ্জ</replace>
			<rules/>
		</pattern>
		<pattern>
			<find>ndh</find>
			<replace>ন্ধ</replace>
			<rules/>
		</pattern>
		<pattern>
			<find>nTh</find>
			<replace>ন্ঠ</replace>
			<rules/>
		</pattern>
		<pattern>
			<find>NTh</find>
			<replace>ণ্ঠ</replace>
			<rules/>
		</pattern>
		<pattern>
			<find>nth</find>
			<replace>ন্থ</replace>
			<rules/>
		</pattern>
		<pattern>
			<find>nkh</find>
			<replace>ঙ্খ</replace>
			<rules/>
		</pattern>
		<pattern>
			<find>ngo</find>
			<replace>ঙ্গ</replace>
			<rules/>
		</pattern>
		<pattern>
			<find>nga</find>
			<replace>ঙ্গা</replace>
			<rules/>
		</pattern>
		<pattern>
			<find>ngi</find>
			<replace>ঙ্গি</replace>
			<rules/>
		</pattern>
		<pattern>
			<find>ngI</find>
			<replace>ঙ্গী</replace>
			<rules/>
		</pattern>
		<pattern>
			<find>ngu</find>
			<replace>ঙ্গু</replace>
			<rules/>
		</pattern>
		<pattern>
			<find>ngU</find>
			<replace>ঙ্গূ</replace>
			<rules/>
		</pattern>
		<pattern>
			<find>nge</find>
			<replace>ঙ্গে</replace>
			<rules/>
		</pattern>
		<pattern>
			<find>ngO</find>
			<replace>ঙ্গো</replace>
			<rules/>
		</pattern>
		<pattern>
			<find>NDh</find>
			<replace>ণ্ঢ</replace>
			<rules/>
		</pattern>
		<pattern>
			<find>nsh</find>
			<replace>নশ</replace>
			<rules/>
		</pattern>
		<pattern>
			<find>Ngr</find>
			<replace>ঙর</replace>
			<rules/>
		</pattern>
		<pattern>
			<find>NGr</find>
			<replace>ঞর</replace>
			<rules/>
		</pattern>
		<pattern>
			<find>ngr</find>
			<replace>ংর</replace>
			<rules/>
		</pattern>
		<pattern>
			<find>nj</find>
			<replace>ঞ্জ</replace>
			<rules/>
		</pattern>
		<pattern>
			<find>Ng</find>
			<replace>ঙ</replace>
			<rules/>
		</pattern>
		<pattern>
			<find>NG</find>
			<replace>ঞ</replace>
			<rules/>
		</pattern>
		<pattern>
			<find>nk</find>
			<replace>ঙ্ক</replace>
			<rules/>
		</pattern>
		<pattern>
			<find>ng</find>
			<replace>ং</replace>
			<rules/>
		</pattern>
		<pattern>
			<find>nn</find>
			<replace>ন্ন</replace>
			<rules/>
		</pattern>
		<pattern>
			<find>NN</find>
			<replace>ণ্ণ</replace>
			<rules/>
		</pattern>
		<pattern>
			<find>Nn</find>
			<replace>ণ্ন</replace>
			<rules/>
		</pattern>
		<pattern>
			<find>nm</find>
			<replace>ন্ম</replace>
			<rules/>
		</pattern>
		<pattern>
			<find>Nm</find>
			<replace>ণ্ম</replace>
			<rules/>
		</pattern>
		<pattern>
			<find>nd</find>
			<replace>ন্দ</replace>
			<rules/>
		</pattern>
		<pattern>
			<find>nT</find>
			<replace>ন্ট</replace>
			<rules/>
		</pattern>
		<pattern>
			<find>NT</find>
			<replace>ণ্ট</replace>
			<rules/>
		</pattern>
		<pattern>
			<find>nD</find>
			<replace>ন্ড</replace>
			<rules/>
		</pattern>
		<pattern>
			<find>ND</find>
			<replace>ণ্ড</replace>
			<rules/>
		</pattern>
		<pattern>
			<find>nt</find>
			<replace>ন্ত</replace>
			<rules/>
		</pattern>
		<pattern>
			<find>ns</find>
			<replace>ন্স</replace>
			<rules/>
		</pattern>
		<pattern>
			<find>nc</find>
			<replace>ঞ্চ</replace>
			<rules/>
		</pattern>
		<pattern>
			<find>n</find>
			<replace>ন</replace>
			<rules/>
		</pattern>
		<pattern>
			<find>N</find>
			<replace>ণ</replace>
			<rules/>
		</pattern>
		<pattern>
			<find>OI`</find>
			<replace>ৈ</replace>
			<rules/>
		</pattern>
		<pattern>
			<find>OU`</find>
			<replace>ৌ</replace>
			<rules/>
		</pattern>
		<pattern>
			<find>O`</find>
			<replace>ো</replace>
			<rules/>
		</pattern>
		<pattern>
			<find>OI</find>
			<replace>ৈ</replace>
			<rules>
				<rule>
					<find>
						<match type="prefix" scope="!consonant" />
					</find>
					<replace>ঐ</replace>
				</rule>
				<rule>
					<find>
						<match type="prefix" scope="punctuation" />
					</find>
					<replace>ঐ</replace>
				</rule>
			</rules>
		</pattern>
		<pattern>
			<find>OU</find>
			<replace>ৌ</replace>
			<rules>
				<rule>
					<find>
						<match type="prefix" scope="!consonant" />
					</find>
					<replace>ঔ</replace>
				</rule>
				<rule>
					<find>
						<match type="prefix" scope="punctuation" />
					</find>
					<replace>ঔ</replace>
				</rule>
			</rules>
		</pattern>
		<pattern>
			<find>O</find>
			<replace>ো</replace>
			<rules>
				<rule>
					<find>
						<match type="prefix" scope="!consonant" />
					</find>
					<replace>ও</replace>
				</rule>
				<rule>
					<find>
						<match type="prefix" scope="punctuation" />
					</find>
					<replace>ও</replace>
				</rule>
			</rules>
		</pattern>
		<pattern>
			<find>phl</find>
			<replace>ফ্ল</replace>
			<rules/>
		</pattern>
		<pattern>
			<find>pT</find>
			<replace>প্ট</replace>
			<rules/>
		</pattern>
		<pattern>
			<find>pt</find>
			<replace>প্ত</replace>
			<rules/>
		</pattern>
		<pattern>
			<find>pn</find>
			<replace>প্ন</replace>
			<rules/>
		</pattern>
		<pattern>
			<find>pp</find>
			<replace>প্প</replace>
			<rules/>
		</pattern>
		<pattern>
			<find>pl</find>
			<replace>প্ল</replace>
			<rules/>
		</pattern>
		<pattern>
			<find>ps</find>
			<replace>প্স</replace>
			<rules/>
		</pattern>
		<pattern>
			<find>ph</find>
			<replace>ফ</replace>
			<rules/>
		</pattern>
		<pattern>
			<find>fl</find>
			<replace>ফ্ল</replace>
			<rules/>
		</pattern>
		<pattern>
			<find>f</find>
			<replace>ফ</replace>
			<rules/>
		</pattern>
		<pattern>
			<find>p</find>
			<replace>প</replace>
			<rules/>
		</pattern>
		<pattern>
			<find>rri`</find>
			<replace>ৃ</replace>
			<rules/>
		</pattern>
		<pattern>
			<find>rri</find>
			<replace>ৃ</replace>
			<rules>
				<rule>
					<find>
						<match type="prefix" scope="!consonant" />
					</find>
					<replace>ঋ</replace>
				</rule>
				<rule>
					<find>
						<match type="prefix" scope="punctuation" />
					</find>
					<replace>ঋ</replace>
				</rule>
			</rules>
		</pattern>
		<pattern>
			<find>rrZ</find>
			<replace>রর‍্য</replace>
			<rules/>
		</pattern>
		<pattern>
			<find>rry</find>
			<replace>রর‍্য</replace>
			<rules/>
		</pattern>
		<pattern>
			<find>rZ</find>
			<!-- NOTE: Invisivle ZWJ here -->
			<replace>র‍্য</replace>
			<rules>
				<rule>
					<find>
						<match type="prefix" scope="consonant" />
						<match type="prefix" scope="!exact">r</match>
						<match type="prefix" scope="!exact">y</match>
						<match type="prefix" scope="!exact">w</match>
						<match type="prefix" scope="!exact">x</match>
					</find>
					<replace>্র্য</replace>
				</rule>
			</rules>
		</pattern>
		<pattern>
			<find>ry</find>
			<!-- NOTE: Invisivle ZWJ here -->
			<replace>র‍্য</replace>
			<rules>
				<rule>
					<find>
						<match type="prefix" scope="consonant" />
						<match type="prefix" scope="!exact">r</match>
						<match type="prefix" scope="!exact">y</match>
						<match type="prefix" scope="!exact">w</match>
						<match type="prefix" scope="!exact">x</match>
					</find>
					<replace>্র্য</replace>
				</rule>
			</rules>
		</pattern>
		<pattern>
			<find>rr</find>
			<replace>রর</replace>
			<rules>
				<rule>
					<find>
						<match type="prefix" scope="!consonant" />
						<match type="suffix" scope="!vowel" />
						<match type="suffix" scope="!exact">r</match>
						<match type="suffix" scope="!punctuation" />
					</find>
					<replace>র্</replace>
				</rule>
				<rule>
					<find>
						<match type="prefix" scope="consonant" />
						<match type="prefix" scope="!exact">r</match>
					</find>
					<replace>্রর</replace>
				</rule>
			</rules>
		</pattern>
		<pattern>
			<find>Rg</find>
			<replace>ড়্গ</replace>
			<rules/>
		</pattern>
		<pattern>
			<find>Rh</find>
			<replace>ঢ়</replace>
			<rules/>
		</pattern>
		<pattern>
			<find>R</find>
			<replace>ড়</replace>
			<rules/>
		</pattern>
		<pattern>
			<find>r</find>
			<replace>র</replace>
			<rules>
				<rule>
					<find>
						<match type="prefix" scope="consonant" />
						<match type="prefix" scope="!exact">r</match>
						<match type="prefix" scope="!exact">y</match>
						<match type="prefix" scope="!exact">w</match>
						<match type="prefix" scope="!exact">x</match>
						<match type="prefix" scope="!exact">Z</match>
					</find>
					<replace>্র</replace>
				</rule>
			</rules>
		</pattern>
		<pattern>
			<find>shch</find>
			<replace>শ্ছ</replace>
			<rules/>
		</pattern>
		<pattern>
			<find>ShTh</find>
			<replace>ষ্ঠ</replace>
			<rules/>
		</pattern>
		<pattern>
			<find>Shph</find>
			<replace>ষ্ফ</replace>
			<rules/>
		</pattern>
		<pattern>
			<find>Sch</find>
			<replace>শ্ছ</replace>
			<rules/>
		</pattern>
		<pattern>
			<find>skl</find>
			<replace>স্ক্ল</replace>
			<rules/>
		</pattern>
		<pattern>
			<find>skh</find>
			<replace>স্খ</replace>
			<rules/>
		</pattern>
		<pattern>
			<find>sth</find>
			<replace>স্থ</replace>
			<rules/>
		</pattern>
		<pattern>
			<find>sph</find>
			<replace>স্ফ</replace>
			<rules/>
		</pattern>
		<pattern>
			<find>shc</find>
			<replace>শ্চ</replace>
			<rules/>
		</pattern>
		<pattern>
			<find>sht</find>
			<replace>শ্ত</replace>
			<rules/>
		</pattern>
		<pattern>
			<find>shn</find>
			<replace>শ্ন</replace>
			<rules/>
		</pattern>
		<pattern>
			<find>shm</find>
			<replace>শ্ম</replace>
			<rules/>
		</pattern>
		<pattern>
			<find>shl</find>
			<replace>শ্ল</replace>
			<rules/>
		</pattern>
		<pattern>
			<find>Shk</find>
			<replace>ষ্ক</replace>
			<rules/>
		</pattern>
		<pattern>
			<find>ShT</find>
			<replace>ষ্ট</replace>
			<rules/>
		</pattern>
		<pattern>
			<find>ShN</find>
			<replace>ষ্ণ</replace>
			<rules/>
		</pattern>
		<pattern>
			<find>Shp</find>
			<replace>ষ্প</replace>
			<rules/>
		</pattern>
		<pattern>
			<find>Shf</find>
			<replace>ষ্ফ</replace>
			<rules/>
		</pattern>
		<pattern>
			<find>Shm</find>
			<replace>ষ্ম</replace>
			<rules/>
		</pattern>
		<pattern>
			<find>spl</find>
			<replace>স্প্ল</replace>
			<rules/>
		</pattern>
		<pattern>
			<find>sk</find>
			<replace>স্ক</replace>
			<rules/>
		</pattern>
		<pattern>
			<find>Sc</find>
			<replace>শ্চ</replace>
			<rules/>
		</pattern>
		<pattern>
			<find>sT</find>
			<replace>স্ট</replace>
			<rules/>
		</pattern>
		<pattern>
			<find>st</find>
			<replace>স্ত</replace>
			<rules/>
		</pattern>
		<pattern>
			<find>sn</find>
			<replace>স্ন</replace>
			<rules/>
		</pattern>
		<pattern>
			<find>sp</find>
			<replace>স্প</replace>
			<rules/>
		</pattern>
		<pattern>
			<find>sf</find>
			<replace>স্ফ</replace>
			<rules/>
		</pattern>
		<pattern>
			<find>sm</find>
			<replace>স্ম</replace>
			<rules/>
		</pattern>
		<pattern>
			<find>sl</find>
			<replace>স্ল</replace>
			<rules/>
		</pattern>
		<pattern>
			<find>sh</find>
			<replace>শ</replace>
			<rules/>
		</pattern>
		<pattern>
			<find>Sc</find>
			<replace>শ্চ</replace>
			<rules/>
		</pattern>
		<pattern>
			<find>St</find>
			<replace>শ্ত</replace>
			<rules/>
		</pattern>
		<pattern>
			<find>Sn</find>
			<replace>শ্ন</replace>
			<rules/>
		</pattern>
		<pattern>
			<find>Sm</find>
			<replace>শ্ম</replace>
			<rules/>
		</pattern>
		<pattern>
			<find>Sl</find>
			<replace>শ্ল</replace>
			<rules/>
		</pattern>
		<pattern>
			<find>Sh</find>
			<replace>ষ</replace>
			<rules/>
		</pattern>
		<pattern>
			<find>s</find>
			<replace>স</replace>
			<rules/>
		</pattern>
		<pattern>
			<find>S</find>
			<replace>শ</replace>
			<rules/>
		</pattern>
		<pattern>
			<find>oo`</find>
			<replace>ু</replace>
			<rules/>
		</pattern>
		<pattern>
			<find>oo</find>
			<replace>ু</replace>
			<rules>
				<rule>
					<find>
						<match type="prefix" scope="!consonant" />
						<match type="suffix" scope="!exact">`</match>
					</find>
					<replace>উ</replace>
				</rule>
				<rule>
					<find>
						<match type="prefix" scope="punctuation" />
						<match type="suffix" scope="!exact">`</match>
					</find>
					<replace>উ</replace>
				</rule>
			</rules>
		</pattern>
		<pattern>
			<find>o`</find>
			<replace/>
			<rules/>
		</pattern>
		<pattern>
			<find>oZ</find>
			<replace>অ্য</replace>
			<rules/>
		</pattern>
		<pattern>
			<find>o</find>
			<replace/>
			<rules>
				<rule>
					<find>
						<match type="prefix" scope="vowel" />
						<match type="prefix" scope="!exact">o</match>
					</find>
					<replace>ও</replace>
				</rule>
				<rule>
					<find>
						<match type="prefix" scope="vowel" />
						<match type="prefix" scope="exact">o</match>
					</find>
					<replace>অ</replace>
				</rule>
				<rule>
					<find>
						<match type="prefix" scope="punctuation" />
					</find>
					<replace>অ</replace>
				</rule>
			</rules>
		</pattern>
		<pattern>
			<find>tth</find>
			<replace>ত্থ</replace>
			<rules/>
		</pattern>
		<pattern>
			<find>t``</find>
			<replace>ৎ</replace>
			<rules/>
		</pattern>
		<pattern>
			<find>TT</find>
			<replace>ট্ট</replace>
			<rules/>
		</pattern>
		<pattern>
			<find>Tm</find>
			<replace>ট্ম</replace>
			<rules/>
		</pattern>
		<pattern>
			<find>Th</find>
			<replace>ঠ</replace>
			<rules/>
		</pattern>
		<pattern>
			<find>tn</find>
			<replace>ত্ন</replace>
			<rules/>
		</pattern>
		<pattern>
			<find>tm</find>
			<replace>ত্ম</replace>
			<rules/>
		</pattern>
		<pattern>
			<find>th</find>
			<replace>থ</replace>
			<rules/>
		</pattern>
		<pattern>
			<find>tt</find>
			<replace>ত্ত</replace>
			<rules/>
		</pattern>
		<pattern>
			<find>T</find>
			<replace>ট</replace>
			<rules/>
		</pattern>
		<pattern>
			<find>t</find>
			<replace>ত</replace>
			<rules/>
		</pattern>
		<pattern>
			<find>aZ</find>
			<replace>অ্যা</replace>
			<rules/>
		</pattern>
		<pattern>
			<find>AZ</find>
			<replace>অ্যা</replace>
			<rules/>
		</pattern>
		<pattern>
			<find>a`</find>
			<replace>া</replace>
			<rules/>
		</pattern>
		<pattern>
			<find>A`</find>
			<replace>া</replace>
			<rules/>
		</pattern>
		<pattern>
			<find>a</find>
			<replace>া</replace>
			<rules>
				<rule>
					<find>
						<match type="prefix" scope="punctuation" />
						<match type="suffix" scope="!exact">`</match>
					</find>
					<replace>আ</replace>
				</rule>
				<rule>
					<find>
						<match type="prefix" scope="!consonant" />
						<match type="prefix" scope="!exact">a</match>
						<match type="suffix" scope="!exact">`</match>
					</find>
					<replace>য়া</replace>
				</rule>
				<rule>
					<find>
						<match type="prefix" scope="exact">a</match>
						<match type="suffix" scope="!exact">`</match>
					</find>
					<replace>আ</replace>
				</rule>
			</rules>
		</pattern>
		<pattern>
			<find>i`</find>
			<replace>ি</replace>
			<rules/>
		</pattern>
		<pattern>
			<find>i</find>
			<replace>ি</replace>
			<rules>
				<rule>
					<find>
						<match type="prefix" scope="!consonant" />
						<match type="suffix" scope="!exact">`</match>
					</find>
					<replace>ই</replace>
				</rule>
				<rule>
					<find>
						<match type="prefix" scope="punctuation" />
						<match type="suffix" scope="!exact">`</match>
					</find>
					<replace>ই</replace>
				</rule>
			</rules>
		</pattern>
		<pattern>
			<find>I`</find>
			<replace>ী</replace>
			<rules/>
		</pattern>
		<pattern>
			<find>I</find>
			<replace>ী</replace>
			<rules>
				<rule>
					<find>
						<match type="prefix" scope="!consonant" />
						<match type="suffix" scope="!exact">`</match>
					</find>
					<replace>ঈ</replace>
				</rule>
				<rule>
					<find>
						<match type="prefix" scope="punctuation" />
						<match type="suffix" scope="!exact">`</match>
					</find>
					<replace>ঈ</replace>
				</rule>
			</rules>
		</pattern>
		<pattern>
			<find>u`</find>
			<replace>ু</replace>
			<rules/>
		</pattern>
		<pattern>
			<find>u</find>
			<replace>ু</replace>
			<rules>
				<rule>
					<find>
						<match type="prefix" scope="!consonant" />
						<match type="suffix" scope="!exact">`</match>
					</find>
					<replace>উ</replace>
				</rule>
				<rule>
					<find>
						<match type="prefix" scope="punctuation" />
						<match type="suffix" scope="!exact">`</match>
					</find>
					<replace>উ</replace>
				</rule>
			</rules>
		</pattern>
		<pattern>
			<find>U`</find>
			<replace>ূ</replace>
			<rules/>
		</pattern>
		<pattern>
			<find>U</find>
			<replace>ূ</replace>
			<rules>
				<rule>
					<find>
						<match type="prefix" scope="!consonant" />
						<match type="suffix" scope="!exact">`</match>
					</find>
					<replace>ঊ</replace>
				</rule>
				<rule>
					<find>
						<match type="prefix" scope="punctuation" />
						<match type="suffix" scope="!exact">`</match>
					</find>
					<replace>ঊ</replace>
				</rule>
			</rules>
		</pattern>
		<pattern>
			<find>ee`</find>
			<replace>ী</replace>
			<rules/>
		</pattern>
		<pattern>
			<find>ee</find>
			<replace>ী</replace>
			<rules>
				<rule>
					<find>
						<match type="prefix" scope="!consonant" />
						<match type="suffix" scope="!exact">`</match>
					</find>
					<replace>ঈ</replace>
				</rule>
				<rule>
					<find>
						<match type="prefix" scope="punctuation" />
						<match type="suffix" scope="!exact">`</match>
					</find>
					<replace>ঈ</replace>
				</rule>
			</rules>
		</pattern>
		<pattern>
			<find>e`</find>
			<replace>ে</replace>
			<rules/>
		</pattern>
		<pattern>
			<find>e</find>
			<replace>ে</replace>
			<rules>
				<rule>
					<find>
						<match type="prefix" scope="!consonant" />
						<match type="suffix" scope="!exact">`</match>
					</find>
					<replace>এ</replace>
				</rule>
				<rule>
					<find>
						<match type="prefix" scope="punctuation" />
						<match type="suffix" scope="!exact">`</match>
					</find>
					<replace>এ</replace>
				</rule>
			</rules>
		</pattern>
		<pattern>
			<find>z</find>
			<replace>য</replace>
			<rules/>
		</pattern>
		<pattern>
			<find>Z</find>
			<replace>্য</replace>
			<rules/>
		</pattern>
		<pattern>
			<find>y</find>
			<replace>্য</replace>
			<rules>
				<rule>
					<find>
						<match type="prefix" scope="!consonant"/>
						<match type="prefix" scope="!punctuation"/>
					</find>
					<replace>য়</replace>
				</rule>
				<rule>
					<find>
						<match type="prefix" scope="punctuation"/>
					</find>
					<replace>ইয়</replace>
				</rule>
			</rules>
		</pattern>
		<pattern>
			<find>Y</find>
			<replace>য়</replace>
			<rules/>
		</pattern>
		<pattern>
			<find>q</find>
			<replace>ক</replace>
			<rules/>
		</pattern>
		<pattern>
			<find>w</find>
			<replace>ও</replace>
			<rules>
				<rule>
					<find>
						<match type="prefix" scope="punctuation"/>
						<match type="suffix" scope="vowel"/>
					</find>
					<replace>ওয়</replace>
				</rule>
				<rule>
					<find>
						<match type="prefix" scope="consonant"/>
					</find>
					<replace>্ব</replace>
				</rule>
			</rules>
		</pattern>
		<pattern>
			<find>x</find>
			<replace>ক্স</replace>
			<rules>
				<rule>
					<find>
						<match type="prefix" scope="punctuation" />
					</find>
					<replace>এক্স</replace>
				</rule>
			</rules>
		</pattern>
		<pattern>
			<find>:`</find>
			<replace>:</replace>
			<rules/>
		</pattern>
		<pattern>
			<find>:</find>
			<replace>ঃ</replace>
			<rules/>
		</pattern>
		<pattern>
			<find>^`</find>
			<replace>^</replace>
			<rules/>
		</pattern>
		<pattern>
			<find>^</find>
			<replace>ঁ</replace>
			<rules/>
		</pattern>
		<pattern>
			<find>,,</find>
			<!-- NOTE: Invisible ZWNJ here -->
			<replace>্‌</replace>
			<rules/>
		</pattern>
		<pattern>
			<find>,</find>
			<replace>,</replace>
			<rules/>
		</pattern>
		<pattern>
			<find>$</find>
			<replace>৳</replace>
			<rules/>
		</pattern>
		<pattern>
			<find>`</find>
			<replace/>
			<rules/>
		</pattern>
	</patterns>
</data>